pennylane_oqcqcaas/__init__.py
pennylane_oqcqcaas/_version.py
pennylane_oqcqcaas/config.toml
pennylane_oqcqcaas/qcaas.py
pennylane_oqcqcaas-0.2.0.dist-info/METADATA
pennylane_oqcqcaas-0.2.0.dist-info/WHEEL
pennylane_oqcqcaas-0.2.0.dist-info/entry_points.txt
pennylane_oqcqcaas-0.2.0.dist-info/RECORD
